django_rabbitmq/__init__.py
django_rabbitmq/admin.py
django_rabbitmq/apps.py
django_rabbitmq/models.py
django_rabbitmq/mq.py
django_rabbitmq/tests.py
django_rabbitmq/views.py
django_rabbitmq/migrations/__init__.py
django_rabbitmq-0.1.3.dist-info/LICENSE
django_rabbitmq-0.1.3.dist-info/METADATA
django_rabbitmq-0.1.3.dist-info/WHEEL
django_rabbitmq-0.1.3.dist-info/top_level.txt
django_rabbitmq-0.1.3.dist-info/RECORD
