Metadata-Version: 2.1
Name: django-rabbitmq
Version: 0.1.3
Summary: Start a RabbitMQ consumer after django server start.
Home-page: https://github.com/wangyuhuiever/django-rabbitmq
Author: Yuhui Wang
Author-email: wangyuhuiever@163.com
License: BSD-3-Clause
Platform: UNKNOWN
Classifier: Programming Language :: Python :: 3
Classifier: License :: OSI Approved :: BSD License
Classifier: Operating System :: OS Independent
Requires-Python: >=3.6
